Metadata-Version: 1.0
Name: London-Borough-Tagger
Version: 0.1
Summary: Tool for tagging coordinates with the London borough they are within.
Home-page: UNKNOWN
Author: Zack Akil
Author-email: zack.akil@pivigo.com
License: MIT
Keywords: london borough tag tagger coordinates
Platform: UNKNOWN
